source_mixpanel/__init__.py
source_mixpanel/backoff_strategy.py
source_mixpanel/components.py
source_mixpanel/config_migrations.py
source_mixpanel/manifest.yaml
source_mixpanel/property_transformation.py
source_mixpanel/run.py
source_mixpanel/schemas/annotations.json
source_mixpanel/schemas/cohort_members.json
source_mixpanel/schemas/cohorts.json
source_mixpanel/schemas/engage.json
source_mixpanel/schemas/export.json
source_mixpanel/schemas/funnel_ids.json
source_mixpanel/schemas/funnels.json
source_mixpanel/schemas/revenue.json
source_mixpanel/source.py
source_mixpanel/spec.json
source_mixpanel/streams.py
source_mixpanel/utils.py
airbyte_source_mixpanel-3.6.1.dist-info/METADATA
airbyte_source_mixpanel-3.6.1.dist-info/WHEEL
airbyte_source_mixpanel-3.6.1.dist-info/entry_points.txt
airbyte_source_mixpanel-3.6.1.dist-info/RECORD
