Metadata-Version: 2.3
Name: airbyte-source-mixpanel
Version: 3.6.1
Summary: Source implementation for Mixpanel.
License: ELv2
Author: Airbyte
Author-email: contact@airbyte.io
Requires-Python: >=3.10,<3.12
Classifier: License :: Other/Proprietary License
Classifier: Programming Language :: Python :: 3
Classifier: Programming Language :: Python :: 3.10
Classifier: Programming Language :: Python :: 3.11
Requires-Dist: airbyte-cdk (>=6,<7)
Requires-Dist: pendulum (==2.1.2)
Requires-Dist: responses (>=0.25.7,<0.26.0)
Project-URL: Documentation, https://docs.airbyte.com/integrations/sources/mixpanel
Project-URL: Homepage, https://airbyte.com
Project-URL: Repository, https://github.com/airbytehq/airbyte
